{
  "parent": "minecraft:recipes/root",
  "rewards": {
    "recipes": [
      "casinocraft:module_card_rougeetnoir"
    ]
  },
  "criteria": {
    "has_paper": {
      "trigger": "minecraft:inventory_changed",
      "conditions": {
        "items": [
          {
            "item": "minecraft:paper",
            "data": 0
          }
        ]
      }
    },
    "has_the_recipe": {
      "trigger": "minecraft:recipe_unlocked",
      "conditions": {
        "recipe": "casinocraft:module_card_rougeetnoir"
      }
    }
  },
  "requirements": [
    [
      "has_paper",
      "has_the_recipe"
    ]
  ]
}